{
    "xesExtensions" : [
        {"name" : "Time", "prefix" : "time", "uri" : "http://www.xes-standard.org/time.xesext"},
        {"name" : "Concept", "prefix" : "concept", "uri" : "http://code.deckfour.org/xes/concept.xesext"},
        {"name" : "Identity", "prefix" : "identity", "uri" : "http://www.xes-standard.org/identity.xesext"}
    ],
    "xesGlobals" : [
        {"key" : "identifier:id", "type" : "int", "value" : "-1", "scope" : "trace"},
        {"key" : "concept:name", "type" : "string", "value" : "Default", "scope" : "event"},
        {"key" : "time:timestamp", "type" : "date", "value" : "0", "scope" : "event"}
    ],
    "xesClassifiers" : [
        {"name" : "Event name", "keys" : [ "concept:name" ]},
        {"name" : "Event timestamp", "keys" : [ "time:timestamp" ]}
    ],
    "switches" : {
        "eventNames" : {
            "0" : "Browse Products on Amazon",
            "1" : "Add Item to Cart",
            "2" : "Pay Order",
            "3" : "Take Payment",
            "4" : "Pick Items",
            "5" : "Place in Bin",
            "6" : "Receive and Package Items",
            "7" : "Send to Carrier Dock",
            "8" : "Load Truck",
            "9" : "Deliver Items",
            "10" : "Receive Items"
        }
    },
    "mappings" : [
        {   
            "indexerFilters" : [
                [ 
                    {"key" : "address", "val" : "PF3G3CHB4F2AFYNB5U2GM7Z3MZ4CQKXH65J4GBQHXJIYOIQ6VEGJXBPBXU", "type" : "address"},
                    {"key" : "min_round", "val" : "14023445", "type" : "int"},
                    {"key" : "max_round", "val" : "14068300", "type" : "int"} 
                ],
                [ 
                    {"key" : "address", "val" : "PF3G3CHB4F2AFYNB5U2GM7Z3MZ4CQKXH65J4GBQHXJIYOIQ6VEGJXBPBXU", "type" : "address"},
                    {"key" : "min_round", "val" : "0", "type" : "int"},
                    {"key" : "max_round", "val" : "1000", "type" : "int"} 
                ]
            ],
            "logMappings" : [
                {
                    "mappingName" : "",
                    "singleTxnFilters" : {
                        "tx-type" : ["pay"]
                    },
                    "traceMappings" : [
                        {
                            "identifier:id" : { "parameter" : { "key" : "note.trace-id", "type" : "int" } },
                            "time:firstEvent" : { "parameter" : { "key" : "round-time", "type" : "date" }, "nullable" : true }
                        }
                    ],
                    "eventMappings" : [
                        {
                            "concept:name" : { "selector" : { "switch" : "eventNames", "value" : "0", "key" : "note.event-name", "type" : "string" }, "nullable" : false },
                            "time:timestamp" : { "parameter" : { "key" : "round-time", "type" : "date" }, "nullable" : false },
                            "actor" : { "parameter" : { "key" : "note.actor", "type" : "string" }, "nullable" : false }
                        },
                        {
                            "concept:name" : { "selector" : { "switch" : "eventNames", "value" : "1", "key" : "note.event-name", "type" : "string" }, "nullable" : false },
                            "time:timestamp" : { "parameter" : { "key" : "round-time", "type" : "date" }, "nullable" : false },
                            "actor" : { "parameter" : { "key" : "note.actor", "type" : "string" }, "nullable" : false },
                            "n-items" : { "parameter" : { "key" : "note.n-items", "type" : "int" }, "nullable" : false }
                        },
                        {
                            "concept:name" : { "selector" : { "switch" : "eventNames", "value" : "2", "key" : "note.event-name", "type" : "string" }, "nullable" : false },
                            "time:timestamp" : { "parameter" : { "key" : "round-time", "type" : "date" }, "nullable" : false },
                            "actor" : { "parameter" : { "key" : "note.actor", "type" : "string" }, "nullable" : false },
                            "n-items" : { "parameter" : { "key" : "note.n-items", "type" : "int" }, "nullable" : false },
                            "attempt-num" : { "parameter" : { "key" : "note.attempt-num", "type" : "int" }, "nullable" : false }
                        },
                        {
                            "concept:name" : { "selector" : { "switch" : "eventNames", "value" : "3", "key" : "note.event-name", "type" : "string" }, "nullable" : false },
                            "time:timestamp" : { "parameter" : { "key" : "round-time", "type" : "date" }, "nullable" : false },
                            "actor" : { "parameter" : { "key" : "note.actor", "type" : "string" }, "nullable" : false },
                            "accepted" : { "parameter" : { "key" : "note.accepted", "type" : "string" }, "nullable" : false }
                        },
                        {
                            "concept:name" : { "selector" : { "switch" : "eventNames", "value" : "4", "key" : "note.event-name", "type" : "string" }, "nullable" : false },
                            "time:timestamp" : { "parameter" : { "key" : "round-time", "type" : "date" }, "nullable" : false },
                            "actor" : { "parameter" : { "key" : "note.actor", "type" : "string" }, "nullable" : false },
                            "n-items" : { "parameter" : { "key" : "note.n-items", "type" : "int" }, "nullable" : false }
                        },
                        {
                            "concept:name" : { "selector" : { "switch" : "eventNames", "value" : "5", "key" : "note.event-name", "type" : "string" }, "nullable" : false },
                            "time:timestamp" : { "parameter" : { "key" : "round-time", "type" : "date" }, "nullable" : false },
                            "actor" : { "parameter" : { "key" : "note.actor", "type" : "string" }, "nullable" : false },
                            "n-items" : { "parameter" : { "key" : "note.n-items", "type" : "int" }, "nullable" : false }
                        },
                        {
                            "concept:name" : { "selector" : { "switch" : "eventNames", "value" : "6", "key" : "note.event-name", "type" : "string" }, "nullable" : false },
                            "time:timestamp" : { "parameter" : { "key" : "round-time", "type" : "date" }, "nullable" : false },
                            "actor" : { "parameter" : { "key" : "note.actor", "type" : "string" }, "nullable" : false },
                            "n-items" : { "parameter" : { "key" : "note.n-items", "type" : "int" }, "nullable" : false }
                        },
                        {
                            "concept:name" : { "selector" : { "switch" : "eventNames", "value" : "7", "key" : "note.event-name", "type" : "string" }, "nullable" : false },
                            "time:timestamp" : { "parameter" : { "key" : "round-time", "type" : "date" }, "nullable" : false },
                            "actor" : { "parameter" : { "key" : "note.actor", "type" : "string" }, "nullable" : false },
                            "n-items" : { "parameter" : { "key" : "note.n-items", "type" : "int" }, "nullable" : false }
                        },
                        {
                            "concept:name" : { "selector" : { "switch" : "eventNames", "value" : "8", "key" : "note.event-name", "type" : "string" }, "nullable" : false },
                            "time:timestamp" : { "parameter" : { "key" : "round-time", "type" : "date" }, "nullable" : false },
                            "actor" : { "parameter" : { "key" : "note.actor", "type" : "string" }, "nullable" : false },
                            "n-items" : { "parameter" : { "key" : "note.n-items", "type" : "int" }, "nullable" : false }
                        },
                        {
                            "concept:name" : { "selector" : { "switch" : "eventNames", "value" : "9", "key" : "note.event-name", "type" : "string" }, "nullable" : false },
                            "time:timestamp" : { "parameter" : { "key" : "round-time", "type" : "date" }, "nullable" : false },
                            "actor" : { "parameter" : { "key" : "note.actor", "type" : "string" }, "nullable" : false },
                            "n-items" : { "parameter" : { "key" : "note.n-items", "type" : "int" }, "nullable" : false }
                        },
                        {
                            "concept:name" : { "selector" : { "switch" : "eventNames", "value" : "10", "key" : "note.event-name", "type" : "string" }, "nullable" : false },
                            "time:timestamp" : { "parameter" : { "key" : "round-time", "type" : "date" }, "nullable" : false },
                            "actor" : { "parameter" : { "key" : "note.actor", "type" : "string" }, "nullable" : false },
                            "n-items" : { "parameter" : { "key" : "note.n-items", "type" : "int" }, "nullable" : false }
                        }
                    ]                
                }
            ]
        }
    ]
}
